protocolinterface/__init__.py
protocolinterface/protocolinterface.py
protocolinterface/validators.py
protocolinterface-0.4.7.dist-info/METADATA
protocolinterface-0.4.7.dist-info/WHEEL
protocolinterface-0.4.7.dist-info/top_level.txt
protocolinterface-0.4.7.dist-info/RECORD
